idor_utils/__init__.py
idor_utils/compress.py
idor_utils/json.py
idor_utils-0.1.1.dist-info/METADATA
idor_utils-0.1.1.dist-info/RECORD
idor_utils-0.1.1.dist-info/WHEEL
idor_utils-0.1.1.dist-info/top_level.txt
